<?xml version="1.0" encoding="UTF-8"?>
<configuration>
    <!-- Console Appender với UTF-8 encoding -->
    <appender name="CONSOLE" class="ch.qos.logback.core.ConsoleAppender">
        <encoder class="ch.qos.logback.core.encoder.LayoutWrappingEncoder">
            <charset>UTF-8</charset>
            <layout class="ch.qos.logback.classic.PatternLayout">
                <pattern>%d{HH:mm:ss.SSS} [%thread] %-5level %logger{36} - %msg%n</pattern>
            </layout>
        </encoder>
    </appender>

    <!-- Root logger -->
    <root level="INFO">
        <appender-ref ref="CONSOLE" />
    </root>
    
    <!-- Giảm log của Spring framework -->
    <logger name="org.springframework" level="WARN"/>
    <logger name="org.hibernate" level="WARN"/>
</configuration>
